{
    "display":"form",
    "settings":{
        "pdf":{
            "id":"1ec0f8ee-6685-5d98-a847-26f67b67d6f0",
            "src":"https://files.form.io/pdf/5692b91fd1028f01000407e3/file/1ec0f8ee-6685-5d98-a847-26f67b67d6f0"
        }
    },
    "components": [
        {
            "id": "eyz97di",
            "key": "status",
            "tags": [],
            "type": "hidden",
            "input": true,
            "label": "status",
            "logic": [],
            "hidden": false,
            "prefix": "",
            "suffix": "",
            "unique": false,
            "widget": {
                "type": "input"
            },
            "dbIndex": false,
            "overlay": {
                "top": "",
                "left": "",
                "page": "",
                "style": "",
                "width": "",
                "height": ""
            },
            "tooltip": "",
            "disabled": false,
            "multiple": false,
            "redrawOn": "",
            "tabindex": "",
            "validate": {
                "custom": "",
                "unique": false,
                "multiple": false,
                "required": false,
                "customPrivate": false,
                "strictDateValidation": false
            },
            "autofocus": false,
            "encrypted": false,
            "hideLabel": false,
            "inputType": "hidden",
            "modalEdit": false,
            "protected": false,
            "refreshOn": "",
            "tableView": false,
            "attributes": {},
            "errorLabel": "",
            "persistent": true,
            "properties": {},
            "validateOn": "change",
            "clearOnHide": true,
            "conditional": {
                "eq": "",
                "show": null,
                "when": null
            },
            "customClass": "",
            "description": "",
            "placeholder": "",
            "defaultValue": "",
            "labelPosition": "top",
            "showCharCount": false,
            "showWordCount": false,
            "calculateValue": "",
            "calculateServer": false,
            "allowMultipleMasks": false,
            "customDefaultValue": "",
            "allowCalculateOverride": false
        },
        {
            "id": "e6koa8o",
            "key": "statusReadable",
            "tags": [],
            "type": "hidden",
            "input": true,
            "label": "status readable",
            "logic": [],
            "hidden": false,
            "prefix": "",
            "suffix": "",
            "unique": false,
            "widget": {
                "type": "input"
            },
            "dbIndex": false,
            "overlay": {
                "top": "",
                "left": "",
                "page": "",
                "style": "",
                "width": "",
                "height": ""
            },
            "tooltip": "",
            "disabled": false,
            "multiple": false,
            "redrawOn": "",
            "tabindex": "",
            "validate": {
                "custom": "",
                "unique": false,
                "multiple": false,
                "required": false,
                "customPrivate": false,
                "strictDateValidation": false
            },
            "autofocus": false,
            "encrypted": false,
            "hideLabel": false,
            "inputType": "hidden",
            "modalEdit": false,
            "protected": false,
            "refreshOn": "",
            "tableView": false,
            "attributes": {},
            "errorLabel": "",
            "persistent": true,
            "properties": {},
            "validateOn": "change",
            "clearOnHide": true,
            "conditional": {
                "eq": "",
                "show": null,
                "when": null
            },
            "customClass": "",
            "description": "",
            "placeholder": "",
            "defaultValue": "",
            "labelPosition": "top",
            "showCharCount": false,
            "showWordCount": false,
            "calculateValue": "",
            "calculateServer": false,
            "allowMultipleMasks": false,
            "customDefaultValue": "var statusLabelEnum = {\n    NEW: 'Nieuwe aanvraag',\n    AWAITING_PAYMENT: 'In afwachting van betaling',\n    AWAITING_APPOINTMENT_CREATION: 'Afspraak met de keuringsarts maken',\n    AWAITING_APPOINTMENT_RESULT: 'Afspraak ingepland',\n    AWAITING_ORDINATION: 'Keuring voltooid',\n    ORDINATION_SENT: 'Uitslag keuring',\n    CARD_READY_FOR_PICK_UP: 'Gehandicaptenparkeerkaart ophalen',\n    CANCELLED: 'Aanvraag geweigerd',\n    COMPLETED: 'Aanvraag afgerond'\n  };\nvalue = statusLabelEnum[data.status];",
            "allowCalculateOverride": false
        },
        {
            "id": "ezooaie",
            "key": "html",
            "tag": "p",
            "tags": [],
            "type": "htmlelement",
            "attrs": [
                {
                    "attr": "",
                    "value": ""
                }
            ],
            "input": false,
            "label": "HTML",
            "logic": [],
            "hidden": false,
            "prefix": "",
            "suffix": "",
            "unique": false,
            "widget": null,
            "content": "<strong>Aanvraaggegevens</strong>\r\n<hr />\r\n<dl class=\"row\">\r\n  <dd class=\"col-12 col-md-4 col-lg-3\">Status</dd>\r\n  <dt class=\"col-12 col-md-8 col-lg-9\">{{data.statusReadable}}</dt>\r\n</dl>",
            "dbIndex": false,
            "overlay": {
                "top": "",
                "left": "",
                "page": "",
                "style": "",
                "width": "",
                "height": ""
            },
            "tooltip": "",
            "disabled": false,
            "multiple": false,
            "redrawOn": "",
            "tabindex": "",
            "validate": {
                "custom": "",
                "unique": false,
                "multiple": false,
                "required": false,
                "customPrivate": false,
                "strictDateValidation": false
            },
            "autofocus": false,
            "className": "",
            "encrypted": false,
            "hideLabel": false,
            "modalEdit": false,
            "protected": false,
            "refreshOn": "",
            "tableView": false,
            "attributes": {},
            "errorLabel": "",
            "persistent": false,
            "properties": {},
            "validateOn": "change",
            "clearOnHide": true,
            "conditional": {
                "eq": "",
                "json": "",
                "show": null,
                "when": null
            },
            "customClass": "",
            "description": "",
            "placeholder": "",
            "defaultValue": null,
            "labelPosition": "top",
            "showCharCount": false,
            "showWordCount": false,
            "calculateValue": "",
            "refreshOnChange": false,
            "customConditional": "",
            "allowMultipleMasks": false,
            "customDefaultValue": "",
            "allowCalculateOverride": false
        },
        {
            "id": "eu8gnnf",
            "key": "application",
            "tags": [],
            "tree": true,
            "type": "container",
            "input": true,
            "label": "application",
            "logic": [],
            "hidden": false,
            "prefix": "",
            "suffix": "",
            "unique": false,
            "widget": null,
            "dbIndex": false,
            "overlay": {
                "top": "",
                "left": "",
                "page": "",
                "style": "",
                "width": "",
                "height": ""
            },
            "tooltip": "",
            "disabled": false,
            "multiple": false,
            "redrawOn": "",
            "tabindex": "",
            "validate": {
                "json": "",
                "custom": "",
                "unique": false,
                "multiple": false,
                "required": false,
                "customMessage": "",
                "customPrivate": false,
                "strictDateValidation": false
            },
            "autofocus": false,
            "encrypted": false,
            "hideLabel": true,
            "modalEdit": false,
            "protected": false,
            "refreshOn": "",
            "tableView": false,
            "attributes": {},
            "components": [
                {
                    "id": "etxpqxu",
                    "key": "hasFee",
                    "tags": [],
                    "type": "hidden",
                    "input": true,
                    "label": "hasFee",
                    "logic": [],
                    "hidden": false,
                    "prefix": "",
                    "suffix": "",
                    "unique": false,
                    "widget": {
                        "type": "input"
                    },
                    "dbIndex": false,
                    "overlay": {
                        "top": "",
                        "left": "",
                        "page": "",
                        "style": "",
                        "width": "",
                        "height": ""
                    },
                    "tooltip": "",
                    "disabled": false,
                    "multiple": false,
                    "redrawOn": "",
                    "tabindex": "",
                    "validate": {
                        "custom": "",
                        "unique": false,
                        "multiple": false,
                        "required": false,
                        "customPrivate": false,
                        "strictDateValidation": false
                    },
                    "autofocus": false,
                    "encrypted": false,
                    "hideLabel": false,
                    "inputType": "hidden",
                    "modalEdit": false,
                    "protected": false,
                    "refreshOn": "",
                    "tableView": false,
                    "attributes": {},
                    "errorLabel": "",
                    "persistent": true,
                    "properties": {},
                    "validateOn": "change",
                    "clearOnHide": true,
                    "conditional": {
                        "eq": "",
                        "show": null,
                        "when": null
                    },
                    "customClass": "",
                    "description": "",
                    "placeholder": "",
                    "defaultValue": "",
                    "labelPosition": "top",
                    "showCharCount": false,
                    "showWordCount": false,
                    "calculateValue": "",
                    "calculateServer": false,
                    "allowMultipleMasks": false,
                    "customDefaultValue": "value = data.application.fee ? 'yes' : 'no';",
                    "allowCalculateOverride": false
                },
                {
                    "id": "etiu6e",
                    "key": "cardTypeReadable",
                    "tags": [],
                    "type": "hidden",
                    "input": true,
                    "label": "cardType readable",
                    "logic": [],
                    "hidden": false,
                    "prefix": "",
                    "suffix": "",
                    "unique": false,
                    "widget": {
                        "type": "input"
                    },
                    "dbIndex": false,
                    "overlay": {
                        "top": "",
                        "left": "",
                        "page": "",
                        "style": "",
                        "width": "",
                        "height": ""
                    },
                    "tooltip": "",
                    "disabled": false,
                    "multiple": false,
                    "redrawOn": "",
                    "tabindex": "",
                    "validate": {
                        "custom": "",
                        "unique": false,
                        "multiple": false,
                        "required": false,
                        "customPrivate": false,
                        "strictDateValidation": false
                    },
                    "autofocus": false,
                    "encrypted": false,
                    "hideLabel": false,
                    "inputType": "hidden",
                    "modalEdit": false,
                    "protected": false,
                    "refreshOn": "",
                    "tableView": false,
                    "attributes": {},
                    "errorLabel": "",
                    "persistent": true,
                    "properties": {},
                    "validateOn": "change",
                    "clearOnHide": true,
                    "conditional": {
                        "eq": "",
                        "show": null,
                        "when": null
                    },
                    "customClass": "",
                    "description": "",
                    "placeholder": "",
                    "defaultValue": "",
                    "labelPosition": "top",
                    "showCharCount": false,
                    "showWordCount": false,
                    "calculateValue": "",
                    "calculateServer": false,
                    "allowMultipleMasks": false,
                    "customDefaultValue": "var labelEnum = {\n    GPKB: 'Bestuurder',\n    GPKP: 'Passagier',\n    GPKBP: 'Combinatie (Bestuurder + Passagier)'\n  };\nvalue = labelEnum[data.application.cardType];",
                    "allowCalculateOverride": false
                },
                {
                    "id": "esjs9h",
                    "key": "html1",
                    "tag": "p",
                    "tags": [],
                    "type": "htmlelement",
                    "attrs": [
                        {
                            "attr": "",
                            "value": ""
                        }
                    ],
                    "input": false,
                    "label": "HTML",
                    "logic": [],
                    "hidden": false,
                    "prefix": "",
                    "suffix": "",
                    "unique": false,
                    "widget": null,
                    "content": "<hr />\r\n<strong>Leges</strong>\r\n<hr/>\r\n<dl class=\"row mb-0\">\r\n  <dd class=\"col-12 col-md-4 col-lg-3\">Kaart type</dd>\r\n  <dt class=\"col-12 col-md-8 col-lg-9\">{{data.application.cardTypeReadable}}</dt>\r\n</dl>\r\n<dl class=\"row mb-0\">\r\n  <dd class=\"col-12 col-md-4 col-lg-3\">Kosten</dd>\r\n  <dt class=\"col-12 col-md-8 col-lg-9\">&euro; {{data.application.fee.amount}}</dt>\r\n</dl>\r\n<dl class=\"row mb-0\">\r\n  <dd class=\"col-12 col-md-4 col-lg-3\">Betaling status</dd>\r\n  <dt class=\"col-12 col-md-8 col-lg-9\">{{ data.application.feePaid ? 'Betaald' : 'Nog niet betaald' }}</dt>\r\n</dl>",
                    "dbIndex": false,
                    "overlay": {
                        "top": "",
                        "left": "",
                        "page": "",
                        "style": "",
                        "width": "",
                        "height": ""
                    },
                    "tooltip": "",
                    "disabled": false,
                    "multiple": false,
                    "redrawOn": "",
                    "tabindex": "",
                    "validate": {
                        "custom": "",
                        "unique": false,
                        "multiple": false,
                        "required": false,
                        "customPrivate": false,
                        "strictDateValidation": false
                    },
                    "autofocus": false,
                    "className": "",
                    "encrypted": false,
                    "hideLabel": false,
                    "modalEdit": false,
                    "protected": false,
                    "refreshOn": "",
                    "tableView": false,
                    "attributes": {},
                    "errorLabel": "",
                    "persistent": false,
                    "properties": {},
                    "validateOn": "change",
                    "clearOnHide": true,
                    "conditional": {
                        "eq": "yes",
                        "json": "",
                        "show": true,
                        "when": "hasFee"
                    },
                    "customClass": "",
                    "description": "",
                    "placeholder": "",
                    "defaultValue": null,
                    "labelPosition": "top",
                    "showCharCount": false,
                    "showWordCount": false,
                    "calculateValue": "",
                    "refreshOnChange": false,
                    "customConditional": "",
                    "allowMultipleMasks": false,
                    "customDefaultValue": "",
                    "allowCalculateOverride": false
                }
            ],
            "errorLabel": "",
            "persistent": true,
            "properties": {},
            "validateOn": "change",
            "clearOnHide": true,
            "conditional": {
                "eq": "",
                "json": "",
                "show": null,
                "when": null
            },
            "customClass": "",
            "description": "",
            "placeholder": "",
            "defaultValue": null,
            "labelPosition": "top",
            "showCharCount": false,
            "showWordCount": false,
            "calculateValue": "",
            "calculateServer": false,
            "customConditional": "",
            "allowMultipleMasks": false,
            "customDefaultValue": "",
            "allowCalculateOverride": false
        },
        {
            "id": "eqble1h",
            "key": "citizen",
            "tags": [],
            "tree": true,
            "type": "container",
            "input": true,
            "label": "citizen",
            "logic": [],
            "hidden": false,
            "prefix": "",
            "suffix": "",
            "unique": false,
            "widget": null,
            "dbIndex": false,
            "overlay": {
                "top": "",
                "left": "",
                "page": "",
                "style": "",
                "width": "",
                "height": ""
            },
            "tooltip": "",
            "disabled": false,
            "multiple": false,
            "redrawOn": "",
            "tabindex": "",
            "validate": {
                "json": "",
                "custom": "",
                "unique": false,
                "multiple": false,
                "required": false,
                "customMessage": "",
                "customPrivate": false,
                "strictDateValidation": false
            },
            "autofocus": false,
            "encrypted": false,
            "hideLabel": true,
            "modalEdit": false,
            "protected": false,
            "refreshOn": "",
            "tableView": false,
            "attributes": {},
            "components": [
                {
                    "id": "elxuspl",
                    "key": "hasCitizen",
                    "tags": [],
                    "type": "hidden",
                    "input": true,
                    "label": "hasCitizen",
                    "logic": [],
                    "hidden": false,
                    "prefix": "",
                    "suffix": "",
                    "unique": false,
                    "widget": {
                        "type": "input"
                    },
                    "dbIndex": false,
                    "overlay": {
                        "top": "",
                        "left": "",
                        "page": "",
                        "style": "",
                        "width": "",
                        "height": ""
                    },
                    "tooltip": "",
                    "disabled": false,
                    "multiple": false,
                    "redrawOn": "",
                    "tabindex": "",
                    "validate": {
                        "custom": "",
                        "unique": false,
                        "multiple": false,
                        "required": false,
                        "customPrivate": false,
                        "strictDateValidation": false
                    },
                    "autofocus": false,
                    "encrypted": false,
                    "hideLabel": false,
                    "inputType": "hidden",
                    "modalEdit": false,
                    "protected": false,
                    "refreshOn": "",
                    "tableView": false,
                    "attributes": {},
                    "errorLabel": "",
                    "persistent": true,
                    "properties": {},
                    "validateOn": "change",
                    "clearOnHide": true,
                    "conditional": {
                        "eq": "",
                        "show": null,
                        "when": null
                    },
                    "customClass": "",
                    "description": "",
                    "placeholder": "",
                    "defaultValue": "",
                    "labelPosition": "top",
                    "showCharCount": false,
                    "showWordCount": false,
                    "calculateValue": "value = !data.citizen.bsn;",
                    "calculateServer": false,
                    "allowMultipleMasks": false,
                    "customDefaultValue": "value = data.citizen.bsn ? 'yes' : 'no';",
                    "allowCalculateOverride": false
                },
                {
                    "id": "ep4yx87",
                    "key": "html2",
                    "tag": "p",
                    "tags": [],
                    "type": "htmlelement",
                    "attrs": [
                        {
                            "attr": "",
                            "value": ""
                        }
                    ],
                    "input": false,
                    "label": "HTML",
                    "logic": [],
                    "hidden": false,
                    "prefix": "",
                    "suffix": "",
                    "unique": false,
                    "widget": null,
                    "content": "<hr/>\r\n<strong>Aanvrager</strong>\r\n<hr/>\r\n<dl class=\"row mb-0\">\r\n  <dd class=\"col-12 col-md-4 col-lg-3\">Burgerservicenummer (BSN)</dd>\r\n  <dt class=\"col-12 col-md-8 col-lg-9\">{{ data.citizen.bsn }}</dt>\r\n</dl>\r\n<dl class=\"row mb-0\">\r\n  <dd class=\"col-12 col-md-4 col-lg-3\">Voornaam</dd>\r\n  <dt class=\"col-12 col-md-8 col-lg-9\">{{ data.citizen.firstName }}</dt>\r\n</dl>\r\n<dl class=\"row mb-0\">\r\n  <dd class=\"col-12 col-md-4 col-lg-3\">Achternaam</dd>\r\n  <dt class=\"col-12 col-md-8 col-lg-9\">{{ data.citizen.lastName }}</dt>\r\n</dl>\r\n<dl class=\"row mb-0\">\r\n  <dd class=\"col-12 col-md-4 col-lg-3\">Adres</dd>\r\n  <dt class=\"col-12 col-md-8 col-lg-9\">\r\n    <address>\r\n      {{ data.citizen.address.street }} {{ data.citizen.address.number }} {{ data.citizen.address.addition }}<br />\r\n      {{ data.citizen.address.postcode }} {{ data.citizen.address.city }}\r\n    </address>\r\n  </dt>\r\n</dl>\r\n<dl class=\"row mb-0\">\r\n  <dd class=\"col-12 col-md-4 col-lg-3\">Telefoonnummer</dd>\r\n  <dt class=\"col-12 col-md-8 col-lg-9\">{{ data.citizen.contactDetails.phoneNumber }}</dt>\r\n</dl>\r\n<dl class=\"row mb-0\">\r\n  <dd class=\"col-12 col-md-4 col-lg-3\">E-mailadres</dd>\r\n  <dt class=\"col-12 col-md-8 col-lg-9\">{{ data.citizen.contactDetails.emailAddress }}</dt>\r\n</dl>",
                    "dbIndex": false,
                    "overlay": {
                        "top": "",
                        "left": "",
                        "page": "",
                        "style": "",
                        "width": "",
                        "height": ""
                    },
                    "tooltip": "",
                    "disabled": false,
                    "multiple": false,
                    "redrawOn": "",
                    "tabindex": "",
                    "validate": {
                        "custom": "",
                        "unique": false,
                        "multiple": false,
                        "required": false,
                        "customPrivate": false,
                        "strictDateValidation": false
                    },
                    "autofocus": false,
                    "className": "",
                    "encrypted": false,
                    "hideLabel": false,
                    "modalEdit": false,
                    "protected": false,
                    "refreshOn": "",
                    "tableView": false,
                    "attributes": {},
                    "errorLabel": "",
                    "persistent": false,
                    "properties": {},
                    "validateOn": "change",
                    "clearOnHide": true,
                    "conditional": {
                        "eq": "yes",
                        "json": "",
                        "show": true,
                        "when": "hasCitizen"
                    },
                    "customClass": "",
                    "description": "",
                    "placeholder": "",
                    "defaultValue": null,
                    "labelPosition": "top",
                    "showCharCount": false,
                    "showWordCount": false,
                    "calculateValue": "",
                    "refreshOnChange": false,
                    "customConditional": "",
                    "allowMultipleMasks": false,
                    "customDefaultValue": "",
                    "allowCalculateOverride": false
                }
            ],
            "errorLabel": "",
            "persistent": true,
            "properties": {},
            "validateOn": "change",
            "clearOnHide": true,
            "conditional": {
                "eq": "",
                "json": "",
                "show": null,
                "when": null
            },
            "customClass": "",
            "description": "",
            "placeholder": "",
            "defaultValue": null,
            "labelPosition": "top",
            "showCharCount": false,
            "showWordCount": false,
            "calculateValue": "",
            "calculateServer": false,
            "customConditional": "",
            "allowMultipleMasks": false,
            "customDefaultValue": "",
            "allowCalculateOverride": false
        },
        {
            "id": "erk6sl",
            "key": "examinationAppointment",
            "tags": [],
            "tree": true,
            "type": "container",
            "input": true,
            "label": "examinationAppointments",
            "logic": [],
            "hidden": false,
            "prefix": "",
            "suffix": "",
            "unique": false,
            "widget": null,
            "dbIndex": false,
            "overlay": {
                "top": "",
                "left": "",
                "page": "",
                "style": "",
                "width": "",
                "height": ""
            },
            "tooltip": "",
            "disabled": false,
            "multiple": false,
            "redrawOn": "",
            "tabindex": "",
            "validate": {
                "json": "",
                "custom": "",
                "unique": false,
                "multiple": false,
                "required": false,
                "customMessage": "",
                "customPrivate": false,
                "strictDateValidation": false
            },
            "autofocus": false,
            "encrypted": false,
            "hideLabel": true,
            "modalEdit": false,
            "protected": false,
            "refreshOn": "",
            "tableView": false,
            "attributes": {},
            "components": [
                {
                    "id": "ehs8cil",
                    "key": "hasExaminationAppointment",
                    "tags": [],
                    "type": "hidden",
                    "input": true,
                    "label": "hasExaminationAppointment",
                    "logic": [],
                    "hidden": false,
                    "prefix": "",
                    "suffix": "",
                    "unique": false,
                    "widget": {
                        "type": "input"
                    },
                    "dbIndex": false,
                    "overlay": {
                        "top": "",
                        "left": "",
                        "page": "",
                        "style": "",
                        "width": "",
                        "height": ""
                    },
                    "tooltip": "",
                    "disabled": false,
                    "multiple": false,
                    "redrawOn": "",
                    "tabindex": "",
                    "validate": {
                        "custom": "",
                        "unique": false,
                        "multiple": false,
                        "required": false,
                        "customPrivate": false,
                        "strictDateValidation": false
                    },
                    "autofocus": false,
                    "encrypted": false,
                    "hideLabel": false,
                    "inputType": "hidden",
                    "modalEdit": false,
                    "protected": false,
                    "refreshOn": "",
                    "tableView": false,
                    "attributes": {},
                    "errorLabel": "",
                    "persistent": true,
                    "properties": {},
                    "validateOn": "change",
                    "clearOnHide": true,
                    "conditional": {
                        "eq": "",
                        "show": null,
                        "when": null
                    },
                    "customClass": "",
                    "description": "",
                    "placeholder": "",
                    "defaultValue": "",
                    "labelPosition": "top",
                    "showCharCount": false,
                    "showWordCount": false,
                    "calculateValue": "",
                    "calculateServer": false,
                    "allowMultipleMasks": false,
                    "customDefaultValue": "value = data.examinationAppointment.appointmentDateTime ? 'yes' : 'no';",
                    "allowCalculateOverride": false
                },
                {
                    "id": "el1li3x",
                    "key": "html3",
                    "tag": "p",
                    "tags": [],
                    "type": "htmlelement",
                    "attrs": [
                        {
                            "attr": "",
                            "value": ""
                        }
                    ],
                    "input": false,
                    "label": "HTML",
                    "logic": [],
                    "hidden": false,
                    "prefix": "",
                    "suffix": "",
                    "unique": false,
                    "widget": null,
                    "content": "<hr/>\r\n<strong>Afspraak medische keuring</strong>\r\n<hr/>\r\n<dl class=\"row mb-0\">\r\n  <dd class=\"col-12 col-md-4 col-lg-3\">Datum</dd>\r\n  <dt class=\"col-12 col-md-8 col-lg-9\">{{ moment(data.examinationAppointment.appointmentDateTime).format('DD-MM-YYYY HH:mm')}}</dt>\r\n</dl>\r\n<dl class=\"row mb-0\">\r\n  <dd class=\"col-12 col-md-4 col-lg-3\">Inwoner aanwezig</dd>\r\n  <dt class=\"col-12 col-md-8 col-lg-9\">{{ data.examination.citizenPresent ? 'Ja' : 'Nee' }}</dt>\r\n</dl>",
                    "dbIndex": false,
                    "overlay": {
                        "top": "",
                        "left": "",
                        "page": "",
                        "style": "",
                        "width": "",
                        "height": ""
                    },
                    "tooltip": "",
                    "disabled": false,
                    "multiple": false,
                    "redrawOn": "",
                    "tabindex": "",
                    "validate": {
                        "custom": "",
                        "unique": false,
                        "multiple": false,
                        "required": false,
                        "customPrivate": false,
                        "strictDateValidation": false
                    },
                    "autofocus": false,
                    "className": "",
                    "encrypted": false,
                    "hideLabel": false,
                    "modalEdit": false,
                    "protected": false,
                    "refreshOn": "",
                    "tableView": false,
                    "attributes": {},
                    "errorLabel": "",
                    "persistent": false,
                    "properties": {},
                    "validateOn": "change",
                    "clearOnHide": true,
                    "conditional": {
                        "eq": "yes",
                        "json": "",
                        "show": true,
                        "when": "hasExaminationAppointment"
                    },
                    "customClass": "",
                    "description": "",
                    "placeholder": "",
                    "defaultValue": null,
                    "labelPosition": "top",
                    "showCharCount": false,
                    "showWordCount": false,
                    "calculateValue": "",
                    "refreshOnChange": false,
                    "customConditional": "",
                    "allowMultipleMasks": false,
                    "customDefaultValue": "",
                    "allowCalculateOverride": false
                }
            ],
            "errorLabel": "",
            "persistent": true,
            "properties": {},
            "validateOn": "change",
            "clearOnHide": true,
            "conditional": {
                "eq": "",
                "json": "",
                "show": null,
                "when": null
            },
            "customClass": "",
            "description": "",
            "placeholder": "",
            "defaultValue": null,
            "labelPosition": "top",
            "showCharCount": false,
            "showWordCount": false,
            "calculateValue": "",
            "calculateServer": false,
            "customConditional": "",
            "allowMultipleMasks": false,
            "customDefaultValue": "",
            "allowCalculateOverride": false
        },
        {
            "id": "eth7rx8",
            "key": "examination",
            "tags": [],
            "tree": true,
            "type": "container",
            "input": true,
            "label": "examination",
            "logic": [],
            "hidden": false,
            "prefix": "",
            "suffix": "",
            "unique": false,
            "widget": null,
            "dbIndex": false,
            "overlay": {
                "top": "",
                "left": "",
                "page": "",
                "style": "",
                "width": "",
                "height": ""
            },
            "tooltip": "",
            "disabled": false,
            "multiple": false,
            "redrawOn": "",
            "tabindex": "",
            "validate": {
                "json": "",
                "custom": "",
                "unique": false,
                "multiple": false,
                "required": false,
                "customMessage": "",
                "customPrivate": false,
                "strictDateValidation": false
            },
            "autofocus": false,
            "encrypted": false,
            "hideLabel": true,
            "modalEdit": false,
            "protected": false,
            "refreshOn": "",
            "tableView": false,
            "attributes": {},
            "components": [
                {
                    "id": "ewnb2n",
                    "key": "hasExamination",
                    "tags": [],
                    "type": "hidden",
                    "input": true,
                    "label": "hasExamination",
                    "logic": [],
                    "hidden": false,
                    "prefix": "",
                    "suffix": "",
                    "unique": false,
                    "widget": {
                        "type": "input"
                    },
                    "dbIndex": false,
                    "overlay": {
                        "top": "",
                        "left": "",
                        "page": "",
                        "style": "",
                        "width": "",
                        "height": ""
                    },
                    "tooltip": "",
                    "disabled": false,
                    "multiple": false,
                    "redrawOn": "",
                    "tabindex": "",
                    "validate": {
                        "custom": "",
                        "unique": false,
                        "multiple": false,
                        "required": false,
                        "customPrivate": false,
                        "strictDateValidation": false
                    },
                    "autofocus": false,
                    "encrypted": false,
                    "hideLabel": false,
                    "inputType": "hidden",
                    "modalEdit": false,
                    "protected": false,
                    "refreshOn": "",
                    "tableView": false,
                    "attributes": {},
                    "errorLabel": "",
                    "persistent": true,
                    "properties": {},
                    "validateOn": "change",
                    "clearOnHide": true,
                    "conditional": {
                        "eq": "",
                        "show": null,
                        "when": null
                    },
                    "customClass": "",
                    "description": "",
                    "placeholder": "",
                    "defaultValue": "",
                    "labelPosition": "top",
                    "showCharCount": false,
                    "showWordCount": false,
                    "calculateValue": "",
                    "calculateServer": false,
                    "allowMultipleMasks": false,
                    "customDefaultValue": "value = data.examination.assessment ? 'yes' : 'no';",
                    "allowCalculateOverride": false
                },
                {
                    "id": "elnxfit",
                    "key": "html4",
                    "tag": "p",
                    "tags": [],
                    "type": "htmlelement",
                    "attrs": [
                        {
                            "attr": "",
                            "value": ""
                        }
                    ],
                    "input": false,
                    "label": "HTML",
                    "logic": [],
                    "hidden": false,
                    "prefix": "",
                    "suffix": "",
                    "unique": false,
                    "widget": null,
                    "content": "<hr/>\r\n<strong>Medische keuring</strong>\r\n<hr/>\r\n<dl class=\"row mb-0\">\r\n  <dd class=\"col-12 col-md-4 col-lg-3\">Keuringsadvies</dd>\r\n  <dt class=\"col-12 col-md-8 col-lg-9\">{{ data.examination.assessment === 'APPLICABLE' ? 'Positief advies' : 'Negatief advies' }}</dt>\r\n</dl>\r\n<dl class=\"row mb-0\" *ngIf=\"document.content.examination.reassessmentRequired\">\r\n  <dd class=\"col-12 col-md-4 col-lg-3\">Vervaldatum keuringsadvies</dd>\r\n  <dt class=\"col-12 col-md-8 col-lg-9\">{{ data.examination.expiryDateAssessment ? moment( data.examination.expiryDateAssessment).format('DD-MM-YYYY') : 'n.v.t.' }}</dt>\r\n</dl>\r\n<dl class=\"row mb-0\">\r\n  <dd class=\"col-12 col-md-4 col-lg-3\">Herkeuring vereist</dd>\r\n  <dt class=\"col-12 col-md-8 col-lg-9\">{{ data.examination.reassessmentRequired ? 'Ja' : 'Nee'}}</dt>\r\n</dl>\r\n<dl class=\"row mb-0\">\r\n  <dd class=\"col-12 col-md-4 col-lg-3\">Foto ontvangen</dd>\r\n  <dt class=\"col-12 col-md-8 col-lg-9\">{{ data.examination.passportPhotoReceived ? 'Ja' : 'Nee'}}</dt>\r\n</dl>",
                    "dbIndex": false,
                    "overlay": {
                        "top": "",
                        "left": "",
                        "page": "",
                        "style": "",
                        "width": "",
                        "height": ""
                    },
                    "tooltip": "",
                    "disabled": false,
                    "multiple": false,
                    "redrawOn": "",
                    "tabindex": "",
                    "validate": {
                        "custom": "",
                        "unique": false,
                        "multiple": false,
                        "required": false,
                        "customPrivate": false,
                        "strictDateValidation": false
                    },
                    "autofocus": false,
                    "className": "",
                    "encrypted": false,
                    "hideLabel": false,
                    "modalEdit": false,
                    "protected": false,
                    "refreshOn": "",
                    "tableView": false,
                    "attributes": {},
                    "errorLabel": "",
                    "persistent": false,
                    "properties": {},
                    "validateOn": "change",
                    "clearOnHide": true,
                    "conditional": {
                        "eq": "yes",
                        "json": "",
                        "show": true,
                        "when": "hasExamination"
                    },
                    "customClass": "",
                    "description": "",
                    "placeholder": "",
                    "defaultValue": null,
                    "labelPosition": "top",
                    "showCharCount": false,
                    "showWordCount": false,
                    "calculateValue": "",
                    "refreshOnChange": false,
                    "customConditional": "",
                    "allowMultipleMasks": false,
                    "customDefaultValue": "",
                    "allowCalculateOverride": false
                }
            ],
            "errorLabel": "",
            "persistent": true,
            "properties": {},
            "validateOn": "change",
            "clearOnHide": true,
            "conditional": {
                "eq": "",
                "json": "",
                "show": null,
                "when": null
            },
            "customClass": "",
            "description": "",
            "placeholder": "",
            "defaultValue": null,
            "labelPosition": "top",
            "showCharCount": false,
            "showWordCount": false,
            "calculateValue": "",
            "calculateServer": false,
            "customConditional": "",
            "allowMultipleMasks": false,
            "customDefaultValue": "",
            "allowCalculateOverride": false
        },
        {
            "id": "eqvpz7q",
            "key": "ordination",
            "tags": [],
            "tree": true,
            "type": "container",
            "input": true,
            "label": "ordination",
            "logic": [],
            "hidden": false,
            "prefix": "",
            "suffix": "",
            "unique": false,
            "widget": null,
            "dbIndex": false,
            "overlay": {
                "top": "",
                "left": "",
                "page": "",
                "style": "",
                "width": "",
                "height": ""
            },
            "tooltip": "",
            "disabled": false,
            "multiple": false,
            "redrawOn": "",
            "tabindex": "",
            "validate": {
                "json": "",
                "custom": "",
                "unique": false,
                "multiple": false,
                "required": false,
                "customMessage": "",
                "customPrivate": false,
                "strictDateValidation": false
            },
            "autofocus": false,
            "encrypted": false,
            "hideLabel": true,
            "modalEdit": false,
            "protected": false,
            "refreshOn": "",
            "tableView": false,
            "attributes": {},
            "components": [
                {
                    "id": "e5ho90c",
                    "key": "hasOrdination",
                    "tags": [],
                    "type": "hidden",
                    "input": true,
                    "label": "hasOrdination",
                    "logic": [],
                    "hidden": false,
                    "prefix": "",
                    "suffix": "",
                    "unique": false,
                    "widget": {
                        "type": "input"
                    },
                    "dbIndex": false,
                    "overlay": {
                        "top": "",
                        "left": "",
                        "page": "",
                        "style": "",
                        "width": "",
                        "height": ""
                    },
                    "tooltip": "",
                    "disabled": false,
                    "multiple": false,
                    "redrawOn": "",
                    "tabindex": "",
                    "validate": {
                        "custom": "",
                        "unique": false,
                        "multiple": false,
                        "required": false,
                        "customPrivate": false,
                        "strictDateValidation": false
                    },
                    "autofocus": false,
                    "encrypted": false,
                    "hideLabel": false,
                    "inputType": "hidden",
                    "modalEdit": false,
                    "protected": false,
                    "refreshOn": "",
                    "tableView": false,
                    "attributes": {},
                    "errorLabel": "",
                    "persistent": true,
                    "properties": {},
                    "validateOn": "change",
                    "clearOnHide": true,
                    "conditional": {
                        "eq": "",
                        "show": null,
                        "when": null
                    },
                    "customClass": "",
                    "description": "",
                    "placeholder": "",
                    "defaultValue": "",
                    "labelPosition": "top",
                    "showCharCount": false,
                    "showWordCount": false,
                    "calculateValue": "",
                    "calculateServer": false,
                    "allowMultipleMasks": false,
                    "customDefaultValue": "value = data.ordination.sentDateTime ? 'yes' : 'no';",
                    "allowCalculateOverride": false
                },
                {
                    "id": "e9l7ew8",
                    "key": "html5",
                    "tag": "p",
                    "tags": [],
                    "type": "htmlelement",
                    "attrs": [
                        {
                            "attr": "",
                            "value": ""
                        }
                    ],
                    "input": false,
                    "label": "HTML",
                    "logic": [],
                    "hidden": false,
                    "prefix": "",
                    "suffix": "",
                    "unique": false,
                    "widget": null,
                    "content": "<hr/>\r\n<strong>Beschikking</strong>\r\n<hr/>\r\n<dl class=\"row mb-0\">\r\n  <dd class=\"col-12 col-md-4 col-lg-3\">Keuringsadvies</dd>\r\n  <dt class=\"col-12 col-md-8 col-lg-9\">{{ data.examination.assessment === 'APPLICABLE' ? 'Positief advies' : 'Negatief advies' }}</dt>\r\n</dl>\r\n<dl class=\"row mb-0\">\r\n  <dd class=\"col-12 col-md-4 col-lg-3\">Verzenddatum</dd>\r\n  <dt class=\"col-12 col-md-8 col-lg-9\"> {{moment(data.ordination.sentDateTime).format('DD-MM-YYYY')}}</dt>\r\n</dl>",
                    "dbIndex": false,
                    "overlay": {
                        "top": "",
                        "left": "",
                        "page": "",
                        "style": "",
                        "width": "",
                        "height": ""
                    },
                    "tooltip": "",
                    "disabled": false,
                    "multiple": false,
                    "redrawOn": "",
                    "tabindex": "",
                    "validate": {
                        "custom": "",
                        "unique": false,
                        "multiple": false,
                        "required": false,
                        "customPrivate": false,
                        "strictDateValidation": false
                    },
                    "autofocus": false,
                    "className": "",
                    "encrypted": false,
                    "hideLabel": false,
                    "modalEdit": false,
                    "protected": false,
                    "refreshOn": "",
                    "tableView": false,
                    "attributes": {},
                    "errorLabel": "",
                    "persistent": false,
                    "properties": {},
                    "validateOn": "change",
                    "clearOnHide": true,
                    "conditional": {
                        "eq": "yes",
                        "json": "",
                        "show": true,
                        "when": "hasOrdination"
                    },
                    "customClass": "",
                    "description": "",
                    "placeholder": "",
                    "defaultValue": null,
                    "labelPosition": "top",
                    "showCharCount": false,
                    "showWordCount": false,
                    "calculateValue": "",
                    "refreshOnChange": false,
                    "customConditional": "",
                    "allowMultipleMasks": false,
                    "customDefaultValue": "",
                    "allowCalculateOverride": false
                }
            ],
            "errorLabel": "",
            "persistent": true,
            "properties": {},
            "validateOn": "change",
            "clearOnHide": true,
            "conditional": {
                "eq": "",
                "json": "",
                "show": null,
                "when": null
            },
            "customClass": "",
            "description": "",
            "placeholder": "",
            "defaultValue": null,
            "labelPosition": "top",
            "showCharCount": false,
            "showWordCount": false,
            "calculateValue": "",
            "calculateServer": false,
            "customConditional": "",
            "allowMultipleMasks": false,
            "customDefaultValue": "",
            "allowCalculateOverride": false
        },
        {
            "id": "e74j76t",
            "key": "card",
            "tags": [],
            "tree": true,
            "type": "container",
            "input": true,
            "label": "card",
            "logic": [],
            "hidden": false,
            "prefix": "",
            "suffix": "",
            "unique": false,
            "widget": null,
            "dbIndex": false,
            "overlay": {
                "top": "",
                "left": "",
                "page": "",
                "style": "",
                "width": "",
                "height": ""
            },
            "tooltip": "",
            "disabled": false,
            "multiple": false,
            "redrawOn": "",
            "tabindex": "",
            "validate": {
                "json": "",
                "custom": "",
                "unique": false,
                "multiple": false,
                "required": false,
                "customMessage": "",
                "customPrivate": false,
                "strictDateValidation": false
            },
            "autofocus": false,
            "encrypted": false,
            "hideLabel": true,
            "modalEdit": false,
            "protected": false,
            "refreshOn": "",
            "tableView": false,
            "attributes": {},
            "components": [
                {
                    "id": "efpraoa",
                    "key": "hasDeposit",
                    "tags": [],
                    "type": "hidden",
                    "input": true,
                    "label": "hasDeposit",
                    "logic": [],
                    "hidden": false,
                    "prefix": "",
                    "suffix": "",
                    "unique": false,
                    "widget": {
                        "type": "input"
                    },
                    "dbIndex": false,
                    "overlay": {
                        "top": "",
                        "left": "",
                        "page": "",
                        "style": "",
                        "width": "",
                        "height": ""
                    },
                    "tooltip": "",
                    "disabled": false,
                    "multiple": false,
                    "redrawOn": "",
                    "tabindex": "",
                    "validate": {
                        "custom": "",
                        "unique": false,
                        "multiple": false,
                        "required": false,
                        "customPrivate": false,
                        "strictDateValidation": false
                    },
                    "autofocus": false,
                    "encrypted": false,
                    "hideLabel": false,
                    "inputType": "hidden",
                    "modalEdit": false,
                    "protected": false,
                    "refreshOn": "",
                    "tableView": false,
                    "attributes": {},
                    "errorLabel": "",
                    "persistent": true,
                    "properties": {},
                    "validateOn": "change",
                    "clearOnHide": true,
                    "conditional": {
                        "eq": "",
                        "show": null,
                        "when": null
                    },
                    "customClass": "",
                    "description": "",
                    "placeholder": "",
                    "defaultValue": "",
                    "labelPosition": "top",
                    "showCharCount": false,
                    "showWordCount": false,
                    "calculateValue": "",
                    "calculateServer": false,
                    "allowMultipleMasks": false,
                    "customDefaultValue": "value = +data.card.deposit.amount > 0 ? 'yes' : 'no';",
                    "allowCalculateOverride": false
                },
                {
                    "id": "e496rz9",
                    "key": "hasRdwRegister",
                    "tags": [],
                    "type": "hidden",
                    "input": true,
                    "label": "hasRDWRegister",
                    "logic": [],
                    "hidden": false,
                    "prefix": "",
                    "suffix": "",
                    "unique": false,
                    "widget": {
                        "type": "input"
                    },
                    "dbIndex": false,
                    "overlay": {
                        "top": "",
                        "left": "",
                        "page": "",
                        "style": "",
                        "width": "",
                        "height": ""
                    },
                    "tooltip": "",
                    "disabled": false,
                    "multiple": false,
                    "redrawOn": "",
                    "tabindex": "",
                    "validate": {
                        "custom": "",
                        "unique": false,
                        "multiple": false,
                        "required": false,
                        "customPrivate": false,
                        "strictDateValidation": false
                    },
                    "autofocus": false,
                    "encrypted": false,
                    "hideLabel": false,
                    "inputType": "hidden",
                    "modalEdit": false,
                    "protected": false,
                    "refreshOn": "",
                    "tableView": false,
                    "attributes": {},
                    "errorLabel": "",
                    "persistent": true,
                    "properties": {},
                    "validateOn": "change",
                    "clearOnHide": true,
                    "conditional": {
                        "eq": "",
                        "show": null,
                        "when": null
                    },
                    "customClass": "",
                    "description": "",
                    "placeholder": "",
                    "defaultValue": "",
                    "labelPosition": "top",
                    "showCharCount": false,
                    "showWordCount": false,
                    "calculateValue": "",
                    "calculateServer": false,
                    "allowMultipleMasks": false,
                    "customDefaultValue": "value = data.card.rdwParentRightId ? 'yes' : 'no';",
                    "allowCalculateOverride": false
                },
                {
                    "id": "ephodf6",
                    "key": "deposit.amount",
                    "tags": [],
                    "type": "hidden",
                    "input": true,
                    "label": "card.deposit.amount",
                    "logic": [],
                    "hidden": false,
                    "prefix": "",
                    "suffix": "",
                    "unique": false,
                    "widget": {
                        "type": "input"
                    },
                    "dbIndex": false,
                    "overlay": {
                        "top": "",
                        "left": "",
                        "page": "",
                        "style": "",
                        "width": "",
                        "height": ""
                    },
                    "tooltip": "",
                    "disabled": false,
                    "multiple": false,
                    "redrawOn": "",
                    "tabindex": "",
                    "validate": {
                        "custom": "",
                        "unique": false,
                        "multiple": false,
                        "required": false,
                        "customPrivate": false,
                        "strictDateValidation": false
                    },
                    "autofocus": false,
                    "encrypted": false,
                    "hideLabel": false,
                    "inputType": "hidden",
                    "modalEdit": false,
                    "protected": false,
                    "refreshOn": "",
                    "tableView": false,
                    "attributes": {},
                    "errorLabel": "",
                    "persistent": true,
                    "properties": {},
                    "validateOn": "change",
                    "clearOnHide": true,
                    "conditional": {
                        "eq": "",
                        "show": null,
                        "when": null
                    },
                    "customClass": "",
                    "description": "",
                    "placeholder": "",
                    "defaultValue": null,
                    "labelPosition": "top",
                    "showCharCount": false,
                    "showWordCount": false,
                    "calculateValue": "",
                    "calculateServer": false,
                    "allowMultipleMasks": false,
                    "customDefaultValue": "",
                    "allowCalculateOverride": false
                },
                {
                    "id": "e9sbpt",
                    "key": "html6",
                    "tag": "p",
                    "tags": [],
                    "type": "htmlelement",
                    "attrs": [
                        {
                            "attr": "",
                            "value": ""
                        }
                    ],
                    "input": false,
                    "label": "HTML",
                    "logic": [],
                    "hidden": false,
                    "prefix": "",
                    "suffix": "",
                    "unique": false,
                    "widget": null,
                    "content": "<hr/>\r\n<strong>Kaartuitgifte en borgregistratie</strong>\r\n<hr/>\r\n<dl class=\"row mb-0\">\r\n  <dd class=\"col-12 col-md-4 col-lg-3\">Borgsom</dd>\r\n  <dt class=\"col-12 col-md-8 col-lg-9\">&euro; {{ data.card.deposit.amount }}.00</dt>\r\n</dl>\r\n<dl class=\"row mb-0\">\r\n  <dd class=\"col-12 col-md-4 col-lg-3\">Betaalmethode</dd>\r\n  <dt class=\"col-12 col-md-8 col-lg-9\">{{ data.card.deposit.paymentMethod === 'PIN' ? 'PIN' : 'Contant' }}</dt>\r\n</dl>",
                    "dbIndex": false,
                    "overlay": {
                        "top": "",
                        "left": "",
                        "page": "",
                        "style": "",
                        "width": "",
                        "height": ""
                    },
                    "tooltip": "",
                    "disabled": false,
                    "multiple": false,
                    "redrawOn": "",
                    "tabindex": "",
                    "validate": {
                        "custom": "",
                        "unique": false,
                        "multiple": false,
                        "required": false,
                        "customPrivate": false,
                        "strictDateValidation": false
                    },
                    "autofocus": false,
                    "className": "",
                    "encrypted": false,
                    "hideLabel": false,
                    "modalEdit": false,
                    "protected": false,
                    "refreshOn": "",
                    "tableView": false,
                    "attributes": {},
                    "errorLabel": "",
                    "persistent": false,
                    "properties": {},
                    "validateOn": "change",
                    "clearOnHide": true,
                    "conditional": {
                        "eq": "yes",
                        "json": "",
                        "show": true,
                        "when": "hasDeposit"
                    },
                    "customClass": "",
                    "description": "",
                    "placeholder": "",
                    "defaultValue": null,
                    "labelPosition": "top",
                    "showCharCount": false,
                    "showWordCount": false,
                    "calculateValue": "",
                    "refreshOnChange": false,
                    "customConditional": "",
                    "allowMultipleMasks": false,
                    "customDefaultValue": "",
                    "allowCalculateOverride": false
                },
                {
                    "id": "elrsztk",
                    "key": "html7",
                    "tag": "p",
                    "tags": [],
                    "type": "htmlelement",
                    "attrs": [
                        {
                            "attr": "",
                            "value": ""
                        }
                    ],
                    "input": false,
                    "label": "HTML",
                    "logic": [],
                    "hidden": false,
                    "prefix": "",
                    "suffix": "",
                    "unique": false,
                    "widget": null,
                    "content": "<hr/>\r\n<strong>RDW</strong>\r\n<hr/>\r\n<dl class=\"row mb-0\">\r\n  <dd class=\"col-12 col-md-4 col-lg-3\">Datum uitgifte</dd>\r\n  <dt class=\"col-12 col-md-8 col-lg-9\">{{ moment(data.card.issueDate).format('DD-MM-YYYY HH:mm') }}</dt>\r\n</dl>\r\n<dl class=\"row mb-0\">\r\n  <dd class=\"col-12 col-md-4 col-lg-3\">Kaartnummer</dd>\r\n  <dt class=\"col-12 col-md-8 col-lg-9\">{{ data.card.cardNumber }}</dt>\r\n</dl>\r\n<dl class=\"row mb-0\">\r\n  <dd class=\"col-12 col-md-4 col-lg-3\">Kaart registratie ID</dd>\r\n  <dt class=\"col-12 col-md-8 col-lg-9\">{{ data.card.rdwParentRightId }}</dt>\r\n</dl>",
                    "dbIndex": false,
                    "overlay": {
                        "top": "",
                        "left": "",
                        "page": "",
                        "style": "",
                        "width": "",
                        "height": ""
                    },
                    "tooltip": "",
                    "disabled": false,
                    "multiple": false,
                    "redrawOn": "",
                    "tabindex": "",
                    "validate": {
                        "custom": "",
                        "unique": false,
                        "multiple": false,
                        "required": false,
                        "customPrivate": false,
                        "strictDateValidation": false
                    },
                    "autofocus": false,
                    "className": "",
                    "encrypted": false,
                    "hideLabel": false,
                    "modalEdit": false,
                    "protected": false,
                    "refreshOn": "",
                    "tableView": false,
                    "attributes": {},
                    "errorLabel": "",
                    "persistent": false,
                    "properties": {},
                    "validateOn": "change",
                    "clearOnHide": true,
                    "conditional": {
                        "eq": "yes",
                        "json": "",
                        "show": true,
                        "when": "hasRdwRegister"
                    },
                    "customClass": "",
                    "description": "",
                    "placeholder": "",
                    "defaultValue": null,
                    "labelPosition": "top",
                    "showCharCount": false,
                    "showWordCount": false,
                    "calculateValue": "",
                    "refreshOnChange": false,
                    "customConditional": "",
                    "allowMultipleMasks": false,
                    "customDefaultValue": "",
                    "allowCalculateOverride": false
                }
            ],
            "errorLabel": "",
            "persistent": true,
            "properties": {},
            "validateOn": "change",
            "clearOnHide": true,
            "conditional": {
                "eq": "",
                "json": "",
                "show": null,
                "when": null
            },
            "customClass": "",
            "description": "",
            "placeholder": "",
            "defaultValue": null,
            "labelPosition": "top",
            "showCharCount": false,
            "showWordCount": false,
            "calculateValue": "",
            "calculateServer": false,
            "customConditional": "",
            "allowMultipleMasks": false,
            "customDefaultValue": "",
            "allowCalculateOverride": false
        }
    ]
}
